[{"useNaturalConf":true,"startTime":"Jul 12, 2021 6:55:09 PM","endTime":"Jul 12, 2021 6:55:14 PM","status":"PASS","level":0,"isLeaf":false,"name":"DataTable And DocString","description":"  DataTable And DocString","bddType":"com.aventstack.extentreports.gherkin.model.Feature","infoMap":{},"children":[{"useNaturalConf":true,"startTime":"Jul 12, 2021 6:55:09 PM","endTime":"Jul 12, 2021 6:55:11 PM","status":"PASS","level":1,"isLeaf":false,"name":"DataTable Scenario","description":"","bddType":"com.aventstack.extentreports.gherkin.model.Scenario","infoMap":{},"children":[{"useNaturalConf":true,"startTime":"Jul 12, 2021 6:55:09 PM","endTime":"Jul 12, 2021 6:55:09 PM","status":"PASS","level":2,"isLeaf":true,"name":"stepdefs.Stepdefs.before(io.cucumber.java.Scenario)","description":"BEFORE","bddType":"com.aventstack.extentreports.gherkin.model.Asterisk","infoMap":{},"children":[],"logs":[{"timestamp":"Jul 12, 2021 6:55:09 PM","status":"INFO","details":"BEFORE HI","seq":0,"infoMap":{}},{"timestamp":"Jul 12, 2021 6:55:09 PM","status":"INFO","details":"BEFORE HELLO","seq":1,"infoMap":{}},{"timestamp":"Jul 12, 2021 6:55:09 PM","status":"PASS","details":"","seq":2,"infoMap":{}}],"media":[],"exceptions":[],"authorSet":[],"categorySet":[],"deviceSet":[],"generatedLog":[]},{"useNaturalConf":true,"startTime":"Jul 12, 2021 6:55:09 PM","endTime":"Jul 12, 2021 6:55:09 PM","status":"PASS","level":2,"isLeaf":true,"name":"Given Hello background","description":"stepdefs.Stepdefs.background()","bddType":"com.aventstack.extentreports.gherkin.model.Given","infoMap":{},"children":[],"logs":[{"timestamp":"Jul 12, 2021 6:55:09 PM","status":"INFO","details":"background","seq":0,"infoMap":{}},{"timestamp":"Jul 12, 2021 6:55:09 PM","status":"PASS","details":"","seq":1,"infoMap":{}}],"media":[],"exceptions":[],"authorSet":[],"categorySet":[],"deviceSet":[],"generatedLog":[]},{"useNaturalConf":true,"startTime":"Jul 12, 2021 6:55:09 PM","endTime":"Jul 12, 2021 6:55:11 PM","status":"PASS","level":2,"isLeaf":true,"name":"Given Customer orders the dishes","description":"stepdefs.Stepdefs.dataTable(java.util.List\u003cjava.util.List\u003cjava.lang.String\u003e\u003e)","bddType":"com.aventstack.extentreports.gherkin.model.Given","infoMap":{},"children":[],"logs":[{"timestamp":"Jul 12, 2021 6:55:09 PM","status":"PASS","details":"\u003ctable class\u003d\u0027markup-table table \u0027\u003e\u003ctr\u003e\u003ctd\u003eone cell Customer orders the dishes\u003c/td\u003e\u003ctd\u003etwo cell\u003c/td\u003e\u003ctd\u003ethree cell\u003c/td\u003e\u003ctd\u003efour cell\u003c/td\u003e\u003ctd\u003efive cell\u003c/td\u003e\u003ctd\u003esix cell\u003c/td\u003e\u003ctd\u003eseven cell\u003c/td\u003e\u003ctd\u003eeight cell\u003c/td\u003e\u003ctd\u003enine cell\u003c/td\u003e\u003ctd\u003eten cell\u003c/td\u003e\u003ctd\u003eeleven cell\u003c/td\u003e\u003ctd\u003etwelve cell\u003c/td\u003e\u003ctd\u003ethirteen cell\u003c/td\u003e\u003ctd\u003efourteen cell\u003c/td\u003e\u003ctd\u003efifteen cell\u003c/td\u003e\u003c/tr\u003e\u003ctr\u003e\u003ctd\u003e1\u003c/td\u003e\u003ctd\u003e2\u003c/td\u003e\u003ctd\u003e3\u003c/td\u003e\u003ctd\u003e4\u003c/td\u003e\u003ctd\u003e5\u003c/td\u003e\u003ctd\u003e6\u003c/td\u003e\u003ctd\u003e7\u003c/td\u003e\u003ctd\u003e8\u003c/td\u003e\u003ctd\u003e9\u003c/td\u003e\u003ctd\u003e10\u003c/td\u003e\u003ctd\u003e11\u003c/td\u003e\u003ctd\u003e12\u003c/td\u003e\u003ctd\u003e13\u003c/td\u003e\u003ctd\u003e14\u003c/td\u003e\u003ctd\u003e15\u003c/td\u003e\u003c/tr\u003e\u003ctr\u003e\u003ctd\u003e1\u003c/td\u003e\u003ctd\u003e2\u003c/td\u003e\u003ctd\u003e3\u003c/td\u003e\u003ctd\u003e4\u003c/td\u003e\u003ctd\u003e5\u003c/td\u003e\u003ctd\u003e6\u003c/td\u003e\u003ctd\u003e7\u003c/td\u003e\u003ctd\u003e8\u003c/td\u003e\u003ctd\u003e9\u003c/td\u003e\u003ctd\u003e10\u003c/td\u003e\u003ctd\u003e11\u003c/td\u003e\u003ctd\u003e12\u003c/td\u003e\u003ctd\u003e13\u003c/td\u003e\u003ctd\u003e14\u003c/td\u003e\u003ctd\u003e15\u003c/td\u003e\u003c/tr\u003e\u003ctr\u003e\u003ctd\u003e1\u003c/td\u003e\u003ctd\u003e2\u003c/td\u003e\u003ctd\u003e3\u003c/td\u003e\u003ctd\u003e4\u003c/td\u003e\u003ctd\u003e5\u003c/td\u003e\u003ctd\u003e6\u003c/td\u003e\u003ctd\u003e7\u003c/td\u003e\u003ctd\u003e8\u003c/td\u003e\u003ctd\u003e9\u003c/td\u003e\u003ctd\u003e10\u003c/td\u003e\u003ctd\u003e11\u003c/td\u003e\u003ctd\u003e12\u003c/td\u003e\u003ctd\u003e13\u003c/td\u003e\u003ctd\u003e14\u003c/td\u003e\u003ctd\u003e15\u003c/td\u003e\u003c/tr\u003e\u003ctr\u003e\u003ctd\u003e1\u003c/td\u003e\u003ctd\u003e2\u003c/td\u003e\u003ctd\u003e3\u003c/td\u003e\u003ctd\u003e4\u003c/td\u003e\u003ctd\u003e5\u003c/td\u003e\u003ctd\u003e6\u003c/td\u003e\u003ctd\u003e7\u003c/td\u003e\u003ctd\u003e8\u003c/td\u003e\u003ctd\u003e9\u003c/td\u003e\u003ctd\u003e10\u003c/td\u003e\u003ctd\u003e11\u003c/td\u003e\u003ctd\u003e12\u003c/td\u003e\u003ctd\u003e13\u003c/td\u003e\u003ctd\u003e14\u003c/td\u003e\u003ctd\u003e15\u003c/td\u003e\u003c/tr\u003e\u003ctr\u003e\u003ctd\u003e1\u003c/td\u003e\u003ctd\u003e2\u003c/td\u003e\u003ctd\u003e3\u003c/td\u003e\u003ctd\u003e4\u003c/td\u003e\u003ctd\u003e5\u003c/td\u003e\u003ctd\u003e6\u003c/td\u003e\u003ctd\u003e7\u003c/td\u003e\u003ctd\u003e8\u003c/td\u003e\u003ctd\u003e9\u003c/td\u003e\u003ctd\u003e10\u003c/td\u003e\u003ctd\u003e11\u003c/td\u003e\u003ctd\u003e12\u003c/td\u003e\u003ctd\u003e13\u003c/td\u003e\u003ctd\u003e14\u003c/td\u003e\u003ctd\u003e15\u003c/td\u003e\u003c/tr\u003e\u003c/table\u003e","seq":0,"infoMap":{}},{"timestamp":"Jul 12, 2021 6:55:11 PM","status":"PASS","details":"","seq":1,"infoMap":{}}],"media":[],"exceptions":[],"authorSet":[],"categorySet":[],"deviceSet":[],"generatedLog":[]},{"useNaturalConf":true,"startTime":"Jul 12, 2021 6:55:11 PM","endTime":"Jul 12, 2021 6:55:11 PM","status":"PASS","level":2,"isLeaf":true,"name":"stepdefs.Stepdefs.after(io.cucumber.java.Scenario)","description":"AFTER","bddType":"com.aventstack.extentreports.gherkin.model.Asterisk","infoMap":{},"children":[],"logs":[{"timestamp":"Jul 12, 2021 6:55:11 PM","status":"INFO","details":"AFTER HI","seq":0,"infoMap":{}},{"timestamp":"Jul 12, 2021 6:55:11 PM","status":"INFO","details":"AFTER HELLO","seq":1,"infoMap":{}},{"timestamp":"Jul 12, 2021 6:55:11 PM","status":"PASS","details":"","seq":2,"infoMap":{}}],"media":[],"exceptions":[],"authorSet":[],"categorySet":[],"deviceSet":[],"generatedLog":[]}],"logs":[],"media":[],"exceptions":[],"authorSet":[],"categorySet":[{"name":"@tabledoc"}],"deviceSet":[],"generatedLog":[]},{"useNaturalConf":true,"startTime":"Jul 12, 2021 6:55:11 PM","endTime":"Jul 12, 2021 6:55:14 PM","status":"PASS","level":1,"isLeaf":false,"name":"Doc String to Custom Object","description":"","bddType":"com.aventstack.extentreports.gherkin.model.Scenario","infoMap":{},"children":[{"useNaturalConf":true,"startTime":"Jul 12, 2021 6:55:11 PM","endTime":"Jul 12, 2021 6:55:11 PM","status":"PASS","level":2,"isLeaf":true,"name":"stepdefs.Stepdefs.before(io.cucumber.java.Scenario)","description":"BEFORE","bddType":"com.aventstack.extentreports.gherkin.model.Asterisk","infoMap":{},"children":[],"logs":[{"timestamp":"Jul 12, 2021 6:55:11 PM","status":"INFO","details":"BEFORE HI","seq":0,"infoMap":{}},{"timestamp":"Jul 12, 2021 6:55:11 PM","status":"INFO","details":"BEFORE HELLO","seq":1,"infoMap":{}},{"timestamp":"Jul 12, 2021 6:55:11 PM","status":"PASS","details":"","seq":2,"infoMap":{}}],"media":[],"exceptions":[],"authorSet":[],"categorySet":[],"deviceSet":[],"generatedLog":[]},{"useNaturalConf":true,"startTime":"Jul 12, 2021 6:55:11 PM","endTime":"Jul 12, 2021 6:55:12 PM","status":"PASS","level":2,"isLeaf":true,"name":"Given Hello background","description":"stepdefs.Stepdefs.background()","bddType":"com.aventstack.extentreports.gherkin.model.Given","infoMap":{},"children":[],"logs":[{"timestamp":"Jul 12, 2021 6:55:11 PM","status":"INFO","details":"background","seq":0,"infoMap":{}},{"timestamp":"Jul 12, 2021 6:55:12 PM","status":"PASS","details":"","seq":1,"infoMap":{}}],"media":[],"exceptions":[],"authorSet":[],"categorySet":[],"deviceSet":[],"generatedLog":[]},{"useNaturalConf":true,"startTime":"Jul 12, 2021 6:55:12 PM","endTime":"Jul 12, 2021 6:55:14 PM","status":"PASS","level":2,"isLeaf":true,"name":"Given the doc string is","description":"stepdefs.Stepdefs.docStr(java.lang.String)","bddType":"com.aventstack.extentreports.gherkin.model.Given","infoMap":{},"children":[],"logs":[{"timestamp":"Jul 12, 2021 6:55:12 PM","status":"PASS","details":"\u003cdiv class\u003d\u0027row\u0027\u003e\r\n \u003cdiv class\u003d\u0027col-md-12\u0027\u003e\r\n  \u003ctextarea readonly class\u003d\u0027code-block\u0027\u003eHello there how r u? Spicy Meatballs for food and drink italian sicily Spicy Meatballs for food and drink italian sicily \n\nDoing great. Spicy Meatballs for food and drink italian sicily\nWhats new? Spicy Meatballs for food and drink italian sicily Spicy Meatballs for food and drink italian sicily\n\nNothing much. Spicy Meatballs for food and drink italian sicily Spicy Meatballs for food and drink italian sicily Spicy Meatballs for food and drink italian sicily\n\nHello there how r u? Hello there how r u? Hello there how r u? Hello there how r u?\nHello there how r u? Hello there how r u? Hello there how r u? Hello there how r u? Hello there how r u?\u003c/textarea\u003e\r\n \u003c/div\u003e\r\n\u003c/div\u003e\r\n","seq":0,"infoMap":{}},{"timestamp":"Jul 12, 2021 6:55:14 PM","status":"PASS","details":"","seq":1,"infoMap":{}}],"media":[],"exceptions":[],"authorSet":[],"categorySet":[],"deviceSet":[],"generatedLog":[]},{"useNaturalConf":true,"startTime":"Jul 12, 2021 6:55:14 PM","endTime":"Jul 12, 2021 6:55:14 PM","status":"PASS","level":2,"isLeaf":true,"name":"stepdefs.Stepdefs.after(io.cucumber.java.Scenario)","description":"AFTER","bddType":"com.aventstack.extentreports.gherkin.model.Asterisk","infoMap":{},"children":[],"logs":[{"timestamp":"Jul 12, 2021 6:55:14 PM","status":"INFO","details":"AFTER HI","seq":0,"infoMap":{}},{"timestamp":"Jul 12, 2021 6:55:14 PM","status":"INFO","details":"AFTER HELLO","seq":1,"infoMap":{}},{"timestamp":"Jul 12, 2021 6:55:14 PM","status":"PASS","details":"","seq":2,"infoMap":{}}],"media":[],"exceptions":[],"authorSet":[],"categorySet":[],"deviceSet":[],"generatedLog":[]}],"logs":[],"media":[],"exceptions":[],"authorSet":[],"categorySet":[{"name":"@tabledoc"}],"deviceSet":[],"generatedLog":[]}],"logs":[],"media":[],"exceptions":[],"authorSet":[],"categorySet":[],"deviceSet":[],"generatedLog":[]}]